chronos_lab/.dataset.example.json
chronos_lab/.env.example
chronos_lab/__init__.py
chronos_lab/_utils.py
chronos_lab/arcdb.py
chronos_lab/aws.py
chronos_lab/dataset.py
chronos_lab/intrinio.py
chronos_lab/mcp_server.py
chronos_lab/plot.py
chronos_lab/settings.py
chronos_lab/sources.py
chronos_lab/storage.py
chronos_lab/analysis/__init__.py
chronos_lab/analysis/driver.py
chronos_lab/analysis/calculation/__init__.py
chronos_lab/analysis/calculation/anomaly.py
chronos_lab/analysis/dag/__init__.py
chronos_lab/analysis/dag/anomaly.py
chronos_lab/analysis/dag/features.py
chronos_lab/analysis/dag/standardize.py
chronos_lab-0.1.8.dist-info/METADATA
chronos_lab-0.1.8.dist-info/WHEEL
chronos_lab-0.1.8.dist-info/entry_points.txt
chronos_lab-0.1.8.dist-info/licenses/LICENSE
chronos_lab-0.1.8.dist-info/RECORD
