Metadata-Version: 2.4
Name: chronos-lab
Version: 0.1.8
Summary: A batteries-included framework for financial time series analysis.
Project-URL: Homepage, https://chronos-lab.vitalik.net/
Project-URL: Repository, https://github.com/vitaliknet/chronos-lab
Project-URL: Changelog, https://github.com/vitaliknet/chronos-lab/blob/main/CHANGELOG.md
Author-email: Vitaly Kuznetsov <chronos-lab@vitalik.net>
License: MIT
License-File: LICENSE
Classifier: Intended Audience :: Financial and Insurance Industry
Classifier: Intended Audience :: Science/Research
Classifier: Programming Language :: Python :: 3.12
Classifier: Programming Language :: Python :: 3.13
Classifier: Topic :: Office/Business :: Financial :: Investment
Classifier: Topic :: Scientific/Engineering :: Information Analysis
Requires-Python: >=3.12
Requires-Dist: numpy>=2.0.2
Requires-Dist: pandas>=2.0.2
Requires-Dist: pydantic-settings>=2.0.2
Provides-Extra: analysis
Requires-Dist: scikit-learn; extra == 'analysis'
Requires-Dist: sf-hamilton[visualization]; extra == 'analysis'
Provides-Extra: arcticdb
Requires-Dist: arcticdb; extra == 'arcticdb'
Provides-Extra: aws
Requires-Dist: boto3; extra == 'aws'
Requires-Dist: botocore; extra == 'aws'
Provides-Extra: docs
Requires-Dist: mkdocs-jupyter; extra == 'docs'
Requires-Dist: mkdocs-material>=9.7.1; extra == 'docs'
Requires-Dist: mkdocs>=1.6.1; extra == 'docs'
Requires-Dist: mkdocstrings[python]>=1.0.0; extra == 'docs'
Provides-Extra: intrinio
Requires-Dist: intrinio-sdk; extra == 'intrinio'
Provides-Extra: mcp
Requires-Dist: fastmcp; extra == 'mcp'
Provides-Extra: visualization
Requires-Dist: matplotlib; extra == 'visualization'
Requires-Dist: mplfinance; extra == 'visualization'
Provides-Extra: yfinance
Requires-Dist: yfinance; extra == 'yfinance'
